{
  "registro": [
    {
      "id": "2634"
    },
    {
      "id": "b254",
      "nombreRegister": "holafgfgf",
      "emailRegister": "luisa@gmail.com",
      "usuarioRegister": "asdfghjk",
      "contraseñaRegister": "12345678"
    },
    {
      "id": "da40",
      "nombreRegister": "holafgfgf",
      "emailRegister": "luisa@gmail.com",
      "usuarioRegister": "12345678",
      "contraseñaRegister": "12345678"
    },
    {
      "id": "b302",
      "nombreRegister": "holafgfgf",
      "emailRegister": "luisa@gmail.com",
      "usuarioRegister": "dfkdfkdfdlf",
      "contraseñaRegister": "asdfertyh"
    },
    {
      "id": "9f47",
      "nombreRegister": "holafgfgf",
      "emailRegister": "luisa@gmail",
      "usuarioRegister": "qweer",
      "contraseñaRegister": "dfdf"
    },
    {
      "id": "ec31",
      "nombreRegister": "holafgfgf",
      "emailRegister": "luisa@gmail",
      "usuarioRegister": "asdffgg",
      "contraseñaRegister": "sfdfdf"
    },
    {
      "id": "67ca",
      "nombreRegister": "",
      "emailRegister": "",
      "usuarioRegister": "",
      "contraseñaRegister": ""
    },
    {
      "id": "ab71",
      "nombreRegister": "",
      "emailRegister": "",
      "usuarioRegister": "",
      "contraseñaRegister": ""
    },
    {
      "id": "fa49",
      "nombreRegister": "hola",
      "emailRegister": "amamma@g.com",
      "usuarioRegister": "asakjk",
      "contraseñaRegister": "1111"
    },
    {
      "id": "a3a5",
      "nombreRegister": "deibys",
      "emailRegister": "hola@gmail.com",
      "usuarioRegister": "hola123",
      "contraseñaRegister": "123"
    },
    {
      "id": "adfa",
      "nombreRegister": "holafgfgf",
      "emailRegister": "jjj@gmail.com",
      "usuarioRegister": "jjj",
      "contraseñaRegister": "jjj"
    },
    {
      "id": "e734",
      "nombreRegister": "holafgfgf",
      "emailRegister": "luisa@g123mail.com",
      "usuarioRegister": "luisaasadsd",
      "contraseñaRegister": "1234556767"
    },
    {
      "id": "5c63",
      "nombreRegister": "holafgfgf",
      "emailRegister": "jj@gmail.com",
      "usuarioRegister": "nn",
      "contraseñaRegister": "nnn"
    },
    {
      "id": "e941",
      "nombreRegister": "hola",
      "emailRegister": "lol@gmail.com",
      "usuarioRegister": "mmm",
      "contraseñaRegister": "nbbb"
    },
    {
      "id": "63cc",
      "nombreRegister": "deibys",
      "emailRegister": "ggg@gmail.com",
      "usuarioRegister": "jjj",
      "contraseñaRegister": "666"
    },
    {
      "id": "dae4",
      "nombreRegister": "deibys",
      "emailRegister": "mm@gmail.com",
      "usuarioRegister": "mm",
      "contraseñaRegister": "rrr"
    },
    {
      "id": "08da",
      "nombreRegister": "deibys",
      "emailRegister": "j@gmail.com",
      "usuarioRegister": "ggg",
      "contraseñaRegister": "123"
    },
    {
      "id": "6d3d",
      "nombreRegister": "deibys",
      "emailRegister": "j@gmail.com",
      "usuarioRegister": "nn",
      "contraseñaRegister": "hhh"
    },
    {
      "id": "7993",
      "nombreRegister": "mm",
      "emailRegister": "m@gmail.com",
      "usuarioRegister": "123",
      "contraseñaRegister": "555"
    },
    {
      "id": "eb0c",
      "nombreRegister": "hola",
      "emailRegister": "m@gmail.com",
      "usuarioRegister": "nn",
      "contraseñaRegister": "123"
    },
    {
      "id": "94c0",
      "nombreRegister": "hola",
      "emailRegister": "a@gmail.com",
      "usuarioRegister": "jjj",
      "contraseñaRegister": "777"
    },
    {
      "id": "af97",
      "nombreRegister": "mmm",
      "emailRegister": "kk@gmail.com",
      "usuarioRegister": "123",
      "contraseñaRegister": "999"
    },
    {
      "id": "9cca",
      "nombreRegister": "holafgfgf",
      "emailRegister": "luisa@gmai.com",
      "usuarioRegister": "ssddf",
      "contraseñaRegister": "sdsdd"
    },
    {
      "id": "e57d",
      "nombreRegister": "holafgfgf",
      "emailRegister": "hola@luisa.com",
      "usuarioRegister": "luisa@",
      "contraseñaRegister": "545"
    },
    {
      "id": "047c",
      "nombreRegister": "holafgfgf",
      "emailRegister": "luisa@gmail.com",
      "usuarioRegister": "qwww",
      "contraseñaRegister": "qwwee"
    },
    {
      "id": "29d1",
      "nombreRegister": "holafgfgf",
      "emailRegister": "uisa@gmail",
      "usuarioRegister": "kkhk",
      "contraseñaRegister": "khk"
    },
    {
      "id": "4f6f",
      "nombreRegister": "holafgfgf",
      "emailRegister": "luisa@gmail.com",
      "usuarioRegister": "asasd",
      "contraseñaRegister": "sdsd"
    },
    {
      "id": "fa2a",
      "nombreRegister": "holafgfgf",
      "emailRegister": "luisa@gmail.com",
      "usuarioRegister": "asass",
      "contraseñaRegister": "sdsd"
    },
    {
      "id": "3042",
      "nombreRegister": "holafgfgf",
      "emailRegister": "lusia@gmail.com",
      "usuarioRegister": "dfkdfldkl",
      "contraseñaRegister": "dfkdfdlfkl"
    },
    {
      "id": "915b",
      "nombreRegister": "holafgfgf",
      "emailRegister": "luisa@gmail.com",
      "usuarioRegister": "dfldfdfdlkfkl",
      "contraseñaRegister": "dfkdfkldflkl"
    },
    {
      "id": "6a9b",
      "nombreRegister": "holafgfgf",
      "emailRegister": "luisa@gmail.com",
      "usuarioRegister": "dsdfdgfggh",
      "contraseñaRegister": "1323434344"
    },
    {
      "id": "9dee",
      "nombreRegister": "luisaperez",
      "emailRegister": "luisas@gmail.com",
      "usuarioRegister": "holaluisape",
      "contraseñaRegister": "1234567890"
    },
    {
      "id": "58f9",
      "nombreRegister": "luisaperez",
      "emailRegister": "luisa@gmail.com",
      "usuarioRegister": "fgfgflgfk",
      "contraseñaRegister": "fdkfdlk"
    },
    {
      "id": "c783",
      "nombreRegister": "luisaperez",
      "emailRegister": "luisa@gmail.com",
      "usuarioRegister": "luisaprez",
      "contraseñaRegister": "dfdgfhghg"
    },
    {
      "id": "a2ff",
      "nombreRegister": "holafgfgf",
      "emailRegister": "luisa@gmail.com",
      "usuarioRegister": "fgfvbvbvb",
      "contraseñaRegister": "fgfgnbjhj"
    },
    {
      "id": "955b",
      "nombreRegister": "luisaperez",
      "emailRegister": "luisa@gmail.com",
      "usuarioRegister": "asderfgt",
      "contraseñaRegister": "asderfgtyh"
    },
    {
      "id": "fd39",
      "nombreRegister": "holafgfgf",
      "emailRegister": "luisa@gmail.com",
      "usuarioRegister": "asderfgt",
      "contraseñaRegister": "asderfgty"
    },
    {
      "id": "5eff",
      "nombreRegister": "holafgfgf",
      "emailRegister": "luias@gmail.com",
      "usuarioRegister": "dfcdkfkffkj",
      "contraseñaRegister": "dfjkdfgfkn"
    },
    {
      "id": "9470",
      "nombreRegister": "holafgfgf",
      "emailRegister": "luisa@gmail.com",
      "usuarioRegister": "dfjdfdkfj",
      "contraseñaRegister": "fkjvckvcjk"
    },
    {
      "id": "4ebc",
      "nombreRegister": "holafgfgf",
      "emailRegister": "luisa@gmail.com",
      "usuarioRegister": "asedfrgghjh",
      "contraseñaRegister": "hghghhjhjggfg"
    },
    {
      "id": "4c12",
      "nombreRegister": "holafgfgf",
      "emailRegister": "luisa@gmail.com",
      "usuarioRegister": "dfdjfdgjfgbfvkj",
      "contraseñaRegister": "xvkjcvkcvck"
    },
    {
      "id": "2afb",
      "nombreRegister": "holafgfgf",
      "emailRegister": "luisa@gmail.com",
      "usuarioRegister": "sfjjjvfbivbjfgji",
      "contraseñaRegister": "cvijcvcjvij"
    },
    {
      "id": "13bc",
      "nombreRegister": "holafgfgf",
      "emailRegister": "luisa@gmail.com",
      "usuarioRegister": "fgfhhjkjk",
      "contraseñaRegister": "dfdfdfdfggfg"
    },
    {
      "id": "eb8c",
      "nombreRegister": "holafgfgf",
      "emailRegister": "luisa@gmail.com",
      "usuarioRegister": "ckldfdjvdflk",
      "contraseñaRegister": "dlkvclvkdvl"
    },
    {
      "id": "9803",
      "nombreRegister": "luisaperez",
      "emailRegister": "luisaperez2115@gmail.com",
      "usuarioRegister": "luisaperez1",
      "contraseñaRegister": "luisaperez1"
    },
    {
      "id": "818d",
      "nombreRegister": "luisaperez",
      "emailRegister": "luisa@gmail.com",
      "usuarioRegister": "luisaasadsd",
      "contraseñaRegister": "luisaperez1"
    },
    {
      "id": "a004",
      "nombreRegister": "holafgfgf",
      "emailRegister": "luisaPerez@gmail.com",
      "usuarioRegister": "skfdfldfk",
      "contraseñaRegister": "dvlkdvdlvk"
    },
    {
      "id": "e78e",
      "nombreRegister": "luisaperez",
      "emailRegister": "luisa@gmail.com",
      "usuarioRegister": "dflkdfldkfdkl",
      "contraseñaRegister": "kclkddlfdkl"
    },
    {
      "id": "c23f",
      "nombreRegister": "luisaperez",
      "emailRegister": "luiasperez@gmail.com",
      "usuarioRegister": "dflkdfldfk",
      "contraseñaRegister": "dvlkdfldfdlkfk"
    },
    {
      "id": "84ff",
      "nombreRegister": "holafgfgf",
      "emailRegister": "luisaPerez@gmail.com",
      "usuarioRegister": "sldsdsdslsl",
      "contraseñaRegister": "dlfkdfdkfdkf"
    },
    {
      "id": "7c2b",
      "nombreRegister": "holafgfgf",
      "emailRegister": "luisa@gmail.com",
      "usuarioRegister": "slkdfldkflkdfkl",
      "contraseñaRegister": "dckldcldkfdkl"
    },
    {
      "id": "7c66",
      "nombreRegister": "holafgfgf",
      "emailRegister": "luisa@gmail.com",
      "usuarioRegister": "sdksdkdksdkls",
      "contraseñaRegister": "ssdksdslkdsld"
    },
    {
      "id": "c397",
      "nombreRegister": "luisaperez",
      "emailRegister": "luisa@gmail.com",
      "usuarioRegister": "sdksdls",
      "contraseñaRegister": "dflfkcdldk"
    },
    {
      "id": "f968",
      "nombreRegister": "luisaperez",
      "emailRegister": "luisa@gmail.com",
      "usuarioRegister": "sdksdls",
      "contraseñaRegister": "3455656767"
    },
    {
      "id": "476e",
      "nombreRegister": "ñiouuii",
      "emailRegister": "luisa@gmail.com",
      "usuarioRegister": "jkjkuiu",
      "contraseñaRegister": "46789"
    }
  ]
}